LICENSE
README.md
setup.cfg
setup.py
HACNet/CNN_dataset.py
HACNet/CNN_model.py
HACNet/CNN_train.py
HACNet/GCN_dataset.py
HACNet/GCN_model.py
HACNet/GCN_train.py
HACNet/Linear_dataset.py
HACNet/Linear_model.py
HACNet/Linear_train.py
HACNet/feature_extraction.py
HACNet/test.py
HACNet.egg-info/PKG-INFO
HACNet.egg-info/SOURCES.txt
HACNet.egg-info/dependency_links.txt
HACNet.egg-info/top_level.txt