Metadata-Version: 2.1
Name: HACNet
Version: 3
Summary: Python package
Home-page: https://github.com/gregory-kyro/HAC-Net/tree/main/src
Download-URL: https://github.com/gregory-kyro/HAC-Net/archive/refs/tags/v3.0.tar.gz
Author: Gregory W. Kyro
Author-email: gregory.kyro@yale.edu
License-File: LICENSE
